{
    "description": "",
    "tags": [],
    "size": {
        "height": 360,
        "width": 640
    },
    "objects": [
        {
            "id": 168617,
            "classId": 7488,
            "description": "",
            "geometryType": "rectangle",
            "labelerLogin": "admin",
            "createdAt": "2023-06-13T20:38:29.702Z",
            "updatedAt": "2023-06-13T20:38:29.702Z",
            "tags": [],
            "classTitle": "insulator",
            "points": {
                "exterior": [
                    [
                        262,
                        46
                    ],
                    [
                        428,
                        359
                    ]
                ],
                "interior": []
            }
        },
        {
            "id": 168616,
            "classId": 7487,
            "description": "",
            "geometryType": "rectangle",
            "labelerLogin": "admin",
            "createdAt": "2023-06-13T20:38:29.702Z",
            "updatedAt": "2023-07-08T10:41:46.431Z",
            "tags": [],
            "classTitle": "broken",
            "points": {
                "exterior": [
                    [
                        266,
                        141
                    ],
                    [
                        341,
                        211
                    ]
                ],
                "interior": []
            }
        }
    ]
}