{
    "description": "",
    "tags": [],
    "size": {
        "height": 360,
        "width": 640
    },
    "objects": [
        {
            "id": 167554,
            "classId": 7488,
            "description": "",
            "geometryType": "rectangle",
            "labelerLogin": "admin",
            "createdAt": "2023-06-13T20:37:31.452Z",
            "updatedAt": "2023-06-13T20:37:31.452Z",
            "tags": [],
            "classTitle": "insulator",
            "points": {
                "exterior": [
                    [
                        101,
                        97
                    ],
                    [
                        639,
                        267
                    ]
                ],
                "interior": []
            }
        },
        {
            "id": 167553,
            "classId": 7487,
            "description": "",
            "geometryType": "rectangle",
            "labelerLogin": "admin",
            "createdAt": "2023-06-13T20:37:31.452Z",
            "updatedAt": "2023-06-13T20:37:31.452Z",
            "tags": [],
            "classTitle": "broken",
            "points": {
                "exterior": [
                    [
                        335,
                        172
                    ],
                    [
                        355,
                        210
                    ]
                ],
                "interior": []
            }
        }
    ]
}