{
    "description": "",
    "tags": [],
    "size": {
        "height": 360,
        "width": 640
    },
    "objects": [
        {
            "id": 168721,
            "classId": 7488,
            "description": "",
            "geometryType": "rectangle",
            "labelerLogin": "admin",
            "createdAt": "2023-06-13T20:38:24.843Z",
            "updatedAt": "2023-06-13T20:38:24.843Z",
            "tags": [],
            "classTitle": "insulator",
            "points": {
                "exterior": [
                    [
                        290,
                        0
                    ],
                    [
                        389,
                        359
                    ]
                ],
                "interior": []
            }
        },
        {
            "id": 168720,
            "classId": 7487,
            "description": "",
            "geometryType": "rectangle",
            "labelerLogin": "admin",
            "createdAt": "2023-06-13T20:38:24.843Z",
            "updatedAt": "2023-06-13T20:38:24.843Z",
            "tags": [],
            "classTitle": "broken",
            "points": {
                "exterior": [
                    [
                        299,
                        199
                    ],
                    [
                        348,
                        222
                    ]
                ],
                "interior": []
            }
        }
    ]
}